airbot_data_collection/__init__.py
airbot_data_collection/__main__.py
airbot_data_collection/basis.py
airbot_data_collection/config.py
airbot_data_collection/main.py
airbot_data_collection/utils.py
airbot_data_collection/common/__init__.py
airbot_data_collection/common/configs/control.py
airbot_data_collection/common/demonstrators/basis.py
airbot_data_collection/common/demonstrators/grouped.py
airbot_data_collection/common/demonstrators/single.py
airbot_data_collection/common/demonstrators/wrapped.py
airbot_data_collection/common/devices/basis.py
airbot_data_collection/common/devices/cameras/intelrealsense.py
airbot_data_collection/common/devices/cameras/mock.py
airbot_data_collection/common/devices/cameras/utils.py
airbot_data_collection/common/devices/cameras/v4l2.py
airbot_data_collection/common/devices/vr/pico.py
airbot_data_collection/common/devices/vr/quest.py
airbot_data_collection/common/environments/basis.py
airbot_data_collection/common/live_data/grouped.py
airbot_data_collection/common/samplers/basis.py
airbot_data_collection/common/samplers/mcap_sampler.py
airbot_data_collection/common/samplers/mcap_sampler_ros.py
airbot_data_collection/common/systems/basis.py
airbot_data_collection/common/systems/data_player.py
airbot_data_collection/common/systems/grouped.py
airbot_data_collection/common/systems/mcap_player.py
airbot_data_collection/common/systems/mock.py
airbot_data_collection/common/systems/wrappers.py
airbot_data_collection/common/utils/benchmark.py
airbot_data_collection/common/utils/codec.py
airbot_data_collection/common/utils/coordinate.py
airbot_data_collection/common/utils/dict_utils.py
airbot_data_collection/common/utils/event_rpc.py
airbot_data_collection/common/utils/http.py
airbot_data_collection/common/utils/interpolate.py
airbot_data_collection/common/utils/progress.py
airbot_data_collection/common/utils/relative_control.py
airbot_data_collection/common/utils/shareable_numpy.py
airbot_data_collection/common/utils/shareable_value.py
airdc-0.6.8.dist-info/METADATA
airdc-0.6.8.dist-info/WHEEL
airdc-0.6.8.dist-info/entry_points.txt
airdc-0.6.8.dist-info/top_level.txt
airdc-0.6.8.dist-info/RECORD
