Metadata-Version: 2.4
Name: airdc
Version: 0.6.8
Summary: AIRDC: Collecting Multimodal Data For Your Robots
Author-email: OpenGHz <latent-shimmer@qq.com>
License: MIT
Project-URL: repository, https://github.com/OpenGHz/AIRBOT-Data-Collection
Requires-Python: >=3.9
Requires-Dist: pydantic
Requires-Dist: numpy
Requires-Dist: more-itertools
Requires-Dist: typing-extensions
Requires-Dist: setproctitle
Requires-Dist: mcap-data-loader==0.1.0
Requires-Dist: inflection
Provides-Extra: airbot
Requires-Dist: ruamel.yaml; extra == "airbot"
Provides-Extra: cv2
Requires-Dist: opencv-python; extra == "cv2"
Provides-Extra: rs
Requires-Dist: pyrealsense2; extra == "rs"
Provides-Extra: web
Requires-Dist: fastapi; extra == "web"
Requires-Dist: uvicorn; extra == "web"
Provides-Extra: v4l2
Requires-Dist: linuxpy; extra == "v4l2"
Requires-Dist: PyTurboJPEG; extra == "v4l2"
Provides-Extra: udev
Requires-Dist: pyudev; extra == "udev"
Provides-Extra: mcap-ros1
Requires-Dist: mcap-ros1-support; extra == "mcap-ros1"
Provides-Extra: image
Requires-Dist: PyTurboJPEG; extra == "image"
Requires-Dist: av; extra == "image"
Provides-Extra: soft
Requires-Dist: pydantic-settings; extra == "soft"
Requires-Dist: omegaconf>=2.3.0; extra == "soft"
Requires-Dist: hydra-zen; extra == "soft"
Requires-Dist: transitions; extra == "soft"
Requires-Dist: bidict; extra == "soft"
Requires-Dist: tqdm; extra == "soft"
Requires-Dist: send2trash>=1.8.3; extra == "soft"
Provides-Extra: hard
Requires-Dist: pynput>=1.8.1; extra == "hard"
Requires-Dist: linuxpy; extra == "hard"
Requires-Dist: PyTurboJPEG; extra == "hard"
Requires-Dist: pyudev; extra == "hard"
Provides-Extra: ml
Requires-Dist: torch; extra == "ml"
Requires-Dist: torchvision; extra == "ml"
Provides-Extra: plt
Requires-Dist: ipykernel; extra == "plt"
Requires-Dist: holoviews; extra == "plt"
Provides-Extra: cfg
Requires-Dist: pydantic-settings; extra == "cfg"
Requires-Dist: omegaconf>=2.3.0; extra == "cfg"
Requires-Dist: hydra-zen; extra == "cfg"
Provides-Extra: basic
Requires-Dist: bidict; extra == "basic"
Requires-Dist: tqdm; extra == "basic"
Requires-Dist: send2trash>=1.8.3; extra == "basic"
Requires-Dist: flatten-dict; extra == "basic"
Provides-Extra: all
Requires-Dist: airdc[basic]; extra == "all"
Requires-Dist: airdc[cfg]; extra == "all"
Requires-Dist: airdc[soft]; extra == "all"
Requires-Dist: airdc[hard]; extra == "all"
Requires-Dist: airdc[cv2]; extra == "all"
